stealth_requests/__init__.py
stealth_requests/response.py
stealth_requests/session.py
stealth_requests/user_agents.json
stealth_requests-2.0.3.dist-info/licenses/LICENSE
stealth_requests-2.0.3.dist-info/METADATA
stealth_requests-2.0.3.dist-info/WHEEL
stealth_requests-2.0.3.dist-info/top_level.txt
stealth_requests-2.0.3.dist-info/RECORD
