Metadata-Version: 2.4
Name: stealth-requests
Version: 2.0.3
Summary: Undetected web-scraping & seamless HTML parsing in Python!
Author-email: Jacob Padilla <stealth-requests@jacobpadilla.com>
License: MIT
Project-URL: Homepage, https://github.com/jpjacobpadilla/Stealth-Requests
Keywords: HTTP,requests,scraping,browser
Requires-Python: >=3.9
License-File: LICENSE
Requires-Dist: curl_cffi
Provides-Extra: parsers
Requires-Dist: lxml; extra == "parsers"
Requires-Dist: html2text; extra == "parsers"
Requires-Dist: beautifulsoup4; extra == "parsers"
Provides-Extra: dev
Requires-Dist: notebook>=7.4.4; extra == "dev"
Dynamic: license-file
